<?xml version="1.0" encoding="UTF-8"?>
<!--Generated by python, Author: Mengze.-->
<osm>
    <node id="20007" lat="-0.00128977" lon="76.51156968">
        <tag k="highway" v="traffic_signals"/>
    </node>
    <node id="30002" lat="-0.00124016" lon="76.51152040"/>
    <node id="30003" lat="-0.00119056" lon="76.51147113"/>
    <node id="30004" lat="-0.00113644" lon="76.51142186"/>
    <node id="30005" lat="-0.00108233" lon="76.51137258">
        <tag k="highway" v="traffic_signals"/>
    </node>
    <way id="30000">
        <nd ref="20007"/>
        <nd ref="30002"/>
        <nd ref="30003"/>
        <nd ref="30004"/>
        <nd ref="30005"/>
        <tag k="name:en" v="double way"/>
    </way>
</osm>
