<?xml version="1.0" encoding="UTF-8"?>
<!--Generated by python, Author: Mengze.-->
<osm>
    <node id="930016" lat="37.84267104" lon="114.39250814">
        <tag k="highway" v="traffic_signals"/>
    </node>
    <node id="1050002" lat="37.84268128" lon="114.39256624"/>
    <node id="1050003" lat="37.84268708" lon="114.39261224"/>
    <node id="1050004" lat="37.84269373" lon="114.39264924"/>
    <node id="1050005" lat="37.84269780" lon="114.39268118"/>
    <node id="1050006" lat="37.84270758" lon="114.39272436"/>
    <node id="1050007" lat="37.84271463" lon="114.39277033"/>
    <node id="1050008" lat="37.84272079" lon="114.39281038"/>
    <node id="1050009" lat="37.84272682" lon="114.39286587"/>
    <node id="1050010" lat="37.84272991" lon="114.39290111"/>
    <node id="1050011" lat="37.84273313" lon="114.39294419"/>
    <node id="1050012" lat="37.84273524" lon="114.39298319"/>
    <node id="1050013" lat="37.84273748" lon="114.39302495"/>
    <node id="1050014" lat="37.84273971" lon="114.39306499"/>
    <node id="1050015" lat="37.84274044" lon="114.39311831"/>
    <node id="1050016" lat="37.84274282" lon="114.39317290">
        <tag k="highway" v="traffic_signals"/>
    </node>
    <way id="1050000">
        <nd ref="930016"/>
        <nd ref="1050002"/>
        <nd ref="1050003"/>
        <nd ref="1050004"/>
        <nd ref="1050005"/>
        <nd ref="1050006"/>
        <nd ref="1050007"/>
        <nd ref="1050008"/>
        <nd ref="1050009"/>
        <nd ref="1050010"/>
        <nd ref="1050011"/>
        <nd ref="1050012"/>
        <nd ref="1050013"/>
        <nd ref="1050014"/>
        <nd ref="1050015"/>
        <nd ref="1050016"/>
        <tag k="name:en" v="double way"/>
    </way>
</osm>
