<?xml version="1.0" encoding="UTF-8"?>
<!--Generated by python, Author: Mengze.-->
<osm>
    <node id="640008" lat="37.83954899" lon="114.39456965">
        <tag k="highway" v="traffic_signals"/>
    </node>
    <node id="680002" lat="37.83955912" lon="114.39454241"/>
    <node id="680003" lat="37.83956303" lon="114.39451513"/>
    <node id="680004" lat="37.83955149" lon="114.39448929"/>
    <node id="680005" lat="37.83952727" lon="114.39446420">
        <tag k="highway" v="traffic_signals"/>
    </node>
    <way id="680000">
        <nd ref="640008"/>
        <nd ref="680002"/>
        <nd ref="680003"/>
        <nd ref="680004"/>
        <nd ref="680005"/>
        <tag k="name:en" v="double way"/>
    </way>
</osm>
