<?xml version="1.0" encoding="UTF-8"?>
<!--Generated by python, Author: Mengze.-->
<osm>
    <node concave_ob="0" id="460022" lat="39.03768234" lon="105.60971783" smoke="0" type="-1" vel="3" wall="0" water="0">
        <tag k="highway" v="traffic_signals"/>
    </node>
    <node concave_ob="0" id="480002" lat="39.03765976" lon="105.60965644" smoke="0" type="-1" vel="3" wall="0" water="0"/>
    <node concave_ob="0" id="480003" lat="39.03764937" lon="105.60963101" smoke="0" type="-1" vel="3" wall="0" water="0"/>
    <node concave_ob="0" id="480004" lat="39.03763926" lon="105.60960605" smoke="0" type="-1" vel="3" wall="0" water="0"/>
    <node concave_ob="0" id="480005" lat="39.03762923" lon="105.60958086" smoke="0" type="-1" vel="3" wall="0" water="0"/>
    <node concave_ob="0" id="480006" lat="39.03762400" lon="105.60956851" smoke="0" type="-1" vel="3" wall="0" water="0"/>
    <node concave_ob="0" id="480007" lat="39.03760829" lon="105.60953159" smoke="0" type="-1" vel="3" wall="0" water="0"/>
    <node concave_ob="0" id="480008" lat="39.03759251" lon="105.60950017" smoke="0" type="-1" vel="3" wall="0" water="0"/>
    <node concave_ob="0" id="480009" lat="39.03757717" lon="105.60947146" smoke="0" type="-1" vel="3" wall="0" water="0"/>
    <node concave_ob="0" id="480010" lat="39.03756600" lon="105.60944380" smoke="0" type="-1" vel="3" wall="0" water="0"/>
    <node concave_ob="0" id="400098" lat="39.03758674" lon="105.60939305" smoke="0" type="-1" vel="3" wall="0" water="0">
        <tag k="highway" v="traffic_signals"/>
    </node>
    <way id="480000">
        <nd ref="460022"/>
        <nd ref="480002"/>
        <nd ref="480003"/>
        <nd ref="480004"/>
        <nd ref="480005"/>
        <nd ref="480006"/>
        <nd ref="480007"/>
        <nd ref="480008"/>
        <nd ref="480009"/>
        <nd ref="480010"/>
        <nd ref="400098"/>
        <tag k="name:en" v="double way"/>
    </way>
</osm>
