<?xml version="1.0" encoding="UTF-8"?>
<!--Generated by python, Author: Mengze.-->
<osm>
    <node concave_ob="0" id="500043" lat="39.03983325" lon="105.61047733" smoke="0" type="-1" vel="10" wall="0" water="0">
        <tag k="highway" v="traffic_signals"/>
    </node>
    <node concave_ob="0" id="520002" lat="39.03986593" lon="105.61049494" smoke="0" type="-1" vel="10" wall="0" water="0"/>
    <node concave_ob="0" id="520003" lat="39.03988331" lon="105.61049938" smoke="0" type="-1" vel="10" wall="0" water="0"/>
    <node concave_ob="0" id="520004" lat="39.03990804" lon="105.61050468" smoke="0" type="-1" vel="10" wall="0" water="0"/>
    <node concave_ob="0" id="520005" lat="39.03992888" lon="105.61051183" smoke="0" type="-1" vel="10" wall="0" water="0"/>
    <node concave_ob="0" id="520006" lat="39.03997208" lon="105.61052373" smoke="0" type="-1" vel="10" wall="0" water="0"/>
    <node concave_ob="0" id="520007" lat="39.03999867" lon="105.61053044" smoke="0" type="-1" vel="10" wall="0" water="0"/>
    <node concave_ob="0" id="520008" lat="39.04002527" lon="105.61053646" smoke="0" type="-1" vel="10" wall="0" water="0"/>
    <node concave_ob="0" id="520009" lat="39.04005247" lon="105.61054173" smoke="0" type="-1" vel="10" wall="0" water="0"/>
    <node concave_ob="0" id="520010" lat="39.04008209" lon="105.61054729" smoke="0" type="-1" vel="10" wall="0" water="0"/>
    <node concave_ob="0" id="520011" lat="39.04012354" lon="105.61055587" smoke="0" type="-1" vel="10" wall="0" water="0"/>
    <node concave_ob="0" id="520012" lat="39.04016920" lon="105.61057199" smoke="0" type="-1" vel="10" wall="0" water="0"/>
    <node concave_ob="0" id="520013" lat="39.04021287" lon="105.61059281" smoke="0" type="-1" vel="10" wall="0" water="0"/>
    <node concave_ob="0" id="520014" lat="39.04024837" lon="105.61061028" smoke="0" type="-1" vel="10" wall="0" water="0"/>
    <node concave_ob="0" id="520015" lat="39.04029043" lon="105.61063181" smoke="0" type="-1" vel="10" wall="0" water="0"/>
    <node concave_ob="0" id="520016" lat="39.04032451" lon="105.61064851" smoke="0" type="-1" vel="10" wall="0" water="0"/>
    <node concave_ob="0" id="520017" lat="39.04036737" lon="105.61066898" smoke="0" type="-1" vel="10" wall="0" water="0"/>
    <node concave_ob="0" id="520018" lat="39.04040524" lon="105.61068679" smoke="0" type="-1" vel="10" wall="0" water="0"/>
    <node concave_ob="0" id="520019" lat="39.04044083" lon="105.61070483" smoke="0" type="-1" vel="10" wall="0" water="0"/>
    <node concave_ob="0" id="520020" lat="39.04048068" lon="105.61072667" smoke="0" type="-1" vel="10" wall="0" water="0"/>
    <node concave_ob="0" id="520021" lat="39.04051056" lon="105.61074356" smoke="0" type="-1" vel="10" wall="0" water="0"/>
    <node concave_ob="0" id="370025" lat="39.04053872" lon="105.61076245" smoke="0" type="-1" vel="10" wall="0" water="0">
        <tag k="highway" v="traffic_signals"/>
    </node>
    <way id="520000">
        <nd ref="500043"/>
        <nd ref="520002"/>
        <nd ref="520003"/>
        <nd ref="520004"/>
        <nd ref="520005"/>
        <nd ref="520006"/>
        <nd ref="520007"/>
        <nd ref="520008"/>
        <nd ref="520009"/>
        <nd ref="520010"/>
        <nd ref="520011"/>
        <nd ref="520012"/>
        <nd ref="520013"/>
        <nd ref="520014"/>
        <nd ref="520015"/>
        <nd ref="520016"/>
        <nd ref="520017"/>
        <nd ref="520018"/>
        <nd ref="520019"/>
        <nd ref="520020"/>
        <nd ref="520021"/>
        <nd ref="370025"/>
        <tag k="name:en" v="double way"/>
    </way>
</osm>
